setup.py
distributions_nd_proj/Binomialdistribution.py
distributions_nd_proj/Gaussiandistribution.py
distributions_nd_proj/Generaldistribution.py
distributions_nd_proj/__init__.py
distributions_nd_proj.egg-info/PKG-INFO
distributions_nd_proj.egg-info/SOURCES.txt
distributions_nd_proj.egg-info/dependency_links.txt
distributions_nd_proj.egg-info/not-zip-safe
distributions_nd_proj.egg-info/top_level.txt